gunicorn_color.py
gunicorn_color-0.1.0.dist-info/DESCRIPTION.rst
gunicorn_color-0.1.0.dist-info/METADATA
gunicorn_color-0.1.0.dist-info/RECORD
gunicorn_color-0.1.0.dist-info/WHEEL
gunicorn_color-0.1.0.dist-info/metadata.json
gunicorn_color-0.1.0.dist-info/top_level.txt
