Metadata-Version: 2.0
Name: gunicorn-color
Version: 0.1.0
Summary: Dead simple access logger for Gunicorn with termcolor support.
Home-page: https://github.com/swistakm/gunicorn-color-logger
Author: Michał Jaworski
Author-email: swistakm@gmail.com
License: BSD
Keywords: gunicorn,color,logger,logging
Platform: UNKNOWN
Classifier: Development Status :: 2 - Pre-Alpha
Classifier: Intended Audience :: Developers
Classifier: Natural Language :: English
Classifier: License :: OSI Approved :: BSD License
Classifier: Operating System :: OS Independent
Classifier: Programming Language :: Python
Classifier: Programming Language :: Python :: 2
Classifier: Programming Language :: Python :: 2.7
Classifier: Programming Language :: Python :: 3
Classifier: Programming Language :: Python :: 3.3
Classifier: Programming Language :: Python :: 3.4
Classifier: Programming Language :: Python :: 3.5
Classifier: Programming Language :: Python :: 3.6
Classifier: Topic :: Internet :: WWW/HTTP :: WSGI
Requires-Dist: termcolor
